keydb_load_balancer/__init__.py
keydb_load_balancer/keydb_monitor.py
keydb_load_balancer/load_balancer.py
keydb_load_balancer/server.py
test/__init__.py
test/test_load_balancer.py
keydb_load_balancer-1.0.0.dist-info/LICENSE.txt
keydb_load_balancer-1.0.0.dist-info/METADATA
keydb_load_balancer-1.0.0.dist-info/WHEEL
keydb_load_balancer-1.0.0.dist-info/top_level.txt
keydb_load_balancer-1.0.0.dist-info/RECORD
